{"nodes": [{"id": "c_beer_programming_personal_project_halloweenconycoding_categories_ai_operating_team_v4_base44_0_main_jsx", "label": "main.jsx", "file_type": "code", "source_file": "C:\\Beer\\Programming\\Personal_Project\\HalloweenConyCoding\\categories\\AI Operating Team\\v4_base44_0\\main.jsx", "source_location": "L1"}], "edges": [{"source": "c_beer_programming_personal_project_halloweenconycoding_categories_ai_operating_team_v4_base44_0_main_jsx", "target": "react", "relation": "imports_from", "context": "import", "confidence": "EXTRACTED", "source_file": "C:\\Beer\\Programming\\Personal_Project\\HalloweenConyCoding\\categories\\AI Operating Team\\v4_base44_0\\main.jsx", "source_location": "L1", "weight": 1.0}, {"source": "c_beer_programming_personal_project_halloweenconycoding_categories_ai_operating_team_v4_base44_0_main_jsx", "target": "client", "relation": "imports_from", "context": "import", "confidence": "EXTRACTED", "source_file": "C:\\Beer\\Programming\\Personal_Project\\HalloweenConyCoding\\categories\\AI Operating Team\\v4_base44_0\\main.jsx", "source_location": "L2", "weight": 1.0}, {"source": "c_beer_programming_personal_project_halloweenconycoding_categories_ai_operating_team_v4_base44_0_main_jsx", "target": "app_jsx", "relation": "imports_from", "context": "import", "confidence": "EXTRACTED", "source_file": "C:\\Beer\\Programming\\Personal_Project\\HalloweenConyCoding\\categories\\AI Operating Team\\v4_base44_0\\main.jsx", "source_location": "L3", "weight": 1.0}, {"source": "c_beer_programming_personal_project_halloweenconycoding_categories_ai_operating_team_v4_base44_0_main_jsx", "target": "index_css", "relation": "imports_from", "context": "import", "confidence": "EXTRACTED", "source_file": "C:\\Beer\\Programming\\Personal_Project\\HalloweenConyCoding\\categories\\AI Operating Team\\v4_base44_0\\main.jsx", "source_location": "L4", "weight": 1.0}], "raw_calls": []}