{"nodes": [{"id": "c_beer_programming_personal_project_halloweenconycoding_categories_ai_operating_team_v4_base44_0_nodedata_jsx", "label": "nodeData.jsx", "file_type": "code", "source_file": "C:\\Beer\\Programming\\Personal_Project\\HalloweenConyCoding\\categories\\AI Operating Team\\v4_base44_0\\nodeData.jsx", "source_location": "L1"}, {"id": "v4_base44_0_nodedata_node_data", "label": "NODE_DATA", "file_type": "code", "source_file": "C:\\Beer\\Programming\\Personal_Project\\HalloweenConyCoding\\categories\\AI Operating Team\\v4_base44_0\\nodeData.jsx", "source_location": "L1"}, {"id": "v4_base44_0_nodedata_node_map", "label": "NODE_MAP", "file_type": "code", "source_file": "C:\\Beer\\Programming\\Personal_Project\\HalloweenConyCoding\\categories\\AI Operating Team\\v4_base44_0\\nodeData.jsx", "source_location": "L277"}, {"id": "v4_base44_0_nodedata_pipeline_colors", "label": "PIPELINE_COLORS", "file_type": "code", "source_file": "C:\\Beer\\Programming\\Personal_Project\\HalloweenConyCoding\\categories\\AI Operating Team\\v4_base44_0\\nodeData.jsx", "source_location": "L279"}, {"id": "v4_base44_0_nodedata_pipeline_labels", "label": "PIPELINE_LABELS", "file_type": "code", "source_file": "C:\\Beer\\Programming\\Personal_Project\\HalloweenConyCoding\\categories\\AI Operating Team\\v4_base44_0\\nodeData.jsx", "source_location": "L286"}, {"id": "v4_base44_0_nodedata_portrait_paths", "label": "PORTRAIT_PATHS()", "file_type": "code", "source_file": "C:\\Beer\\Programming\\Personal_Project\\HalloweenConyCoding\\categories\\AI Operating Team\\v4_base44_0\\nodeData.jsx", "source_location": "L293"}, {"id": "v4_base44_0_nodedata_sigils", "label": "SIGILS", "file_type": "code", "source_file": "C:\\Beer\\Programming\\Personal_Project\\HalloweenConyCoding\\categories\\AI Operating Team\\v4_base44_0\\nodeData.jsx", "source_location": "L298"}, {"id": "v4_base44_0_nodedata_sigilmap", "label": "sigilMap", "file_type": "code", "source_file": "C:\\Beer\\Programming\\Personal_Project\\HalloweenConyCoding\\categories\\AI Operating Team\\v4_base44_0\\nodeData.jsx", "source_location": "L310"}], "edges": [{"source": "c_beer_programming_personal_project_halloweenconycoding_categories_ai_operating_team_v4_base44_0_nodedata_jsx", "target": "v4_base44_0_nodedata_node_data", "relation": "contains", "confidence": "EXTRACTED", "source_file": "C:\\Beer\\Programming\\Personal_Project\\HalloweenConyCoding\\categories\\AI Operating Team\\v4_base44_0\\nodeData.jsx", "source_location": "L1", "weight": 1.0}, {"source": "c_beer_programming_personal_project_halloweenconycoding_categories_ai_operating_team_v4_base44_0_nodedata_jsx", "target": "v4_base44_0_nodedata_node_map", "relation": "contains", "confidence": "EXTRACTED", "source_file": "C:\\Beer\\Programming\\Personal_Project\\HalloweenConyCoding\\categories\\AI Operating Team\\v4_base44_0\\nodeData.jsx", "source_location": "L277", "weight": 1.0}, {"source": "c_beer_programming_personal_project_halloweenconycoding_categories_ai_operating_team_v4_base44_0_nodedata_jsx", "target": "v4_base44_0_nodedata_pipeline_colors", "relation": "contains", "confidence": "EXTRACTED", "source_file": "C:\\Beer\\Programming\\Personal_Project\\HalloweenConyCoding\\categories\\AI Operating Team\\v4_base44_0\\nodeData.jsx", "source_location": "L279", "weight": 1.0}, {"source": "c_beer_programming_personal_project_halloweenconycoding_categories_ai_operating_team_v4_base44_0_nodedata_jsx", "target": "v4_base44_0_nodedata_pipeline_labels", "relation": "contains", "confidence": "EXTRACTED", "source_file": "C:\\Beer\\Programming\\Personal_Project\\HalloweenConyCoding\\categories\\AI Operating Team\\v4_base44_0\\nodeData.jsx", "source_location": "L286", "weight": 1.0}, {"source": "c_beer_programming_personal_project_halloweenconycoding_categories_ai_operating_team_v4_base44_0_nodedata_jsx", "target": "v4_base44_0_nodedata_portrait_paths", "relation": "contains", "confidence": "EXTRACTED", "source_file": "C:\\Beer\\Programming\\Personal_Project\\HalloweenConyCoding\\categories\\AI Operating Team\\v4_base44_0\\nodeData.jsx", "source_location": "L293", "weight": 1.0}, {"source": "c_beer_programming_personal_project_halloweenconycoding_categories_ai_operating_team_v4_base44_0_nodedata_jsx", "target": "v4_base44_0_nodedata_sigils", "relation": "contains", "confidence": "EXTRACTED", "source_file": "C:\\Beer\\Programming\\Personal_Project\\HalloweenConyCoding\\categories\\AI Operating Team\\v4_base44_0\\nodeData.jsx", "source_location": "L298", "weight": 1.0}, {"source": "c_beer_programming_personal_project_halloweenconycoding_categories_ai_operating_team_v4_base44_0_nodedata_jsx", "target": "v4_base44_0_nodedata_sigilmap", "relation": "contains", "confidence": "EXTRACTED", "source_file": "C:\\Beer\\Programming\\Personal_Project\\HalloweenConyCoding\\categories\\AI Operating Team\\v4_base44_0\\nodeData.jsx", "source_location": "L310", "weight": 1.0}], "raw_calls": []}